<annotation>
	<folder>train</folder>
	<filename>IMG_20190906_105258.jpg</filename>
	<path>D:\NECTEC\Kid-Bright_AI\Temp\resim (2)\root\tfdata\images\train\IMG_20190906_105258.jpg</path>
	<source>
		<database>Unknown</database>
	</source>
	<size>
		<width>480</width>
		<height>640</height>
		<depth>3</depth>
	</size>
	<segmented>0</segmented>
	<object>
		<name>nekobus</name>
		<pose>Unspecified</pose>
		<truncated>0</truncated>
		<difficult>0</difficult>
		<bndbox>
			<xmin>49</xmin>
			<ymin>305</ymin>
			<xmax>277</xmax>
			<ymax>554</ymax>
		</bndbox>
	</object>
	<object>
		<name>totoro</name>
		<pose>Unspecified</pose>
		<truncated>0</truncated>
		<difficult>0</difficult>
		<bndbox>
			<xmin>185</xmin>
			<ymin>81</ymin>
			<xmax>417</xmax>
			<ymax>312</ymax>
		</bndbox>
	</object>
</annotation>
